Metadata-Version: 2.1
Name: ntpl
Version: 0.0.3
Summary: Minimal library to modify and render HTML.
Home-page: https://github.com/chr15m/ntpl
Author: Chris McCormick
Author-email: chris@mccormick.cx
License: LICENSE.txt
Platform: UNKNOWN
